PyScriptTools/__init__.py
PyScriptTools/__main__.py
PyScriptTools/exceptions.py
PyScriptTools/validators.py
PyScriptTools/base/__author__.py
PyScriptTools/base/__init__.py
PyScriptTools/base/__version__.py
PyScriptTools/tools/__init__.py
PyScriptTools/tools/CPUTools/__init__.py
PyScriptTools/tools/DiskTools/__init__.py
PyScriptTools/tools/GPUTools/__init__.py
PyScriptTools/tools/NetworkTools/__init__.py
PyScriptTools/tools/OtherTools/__init__.py
PyScriptTools/tools/RAMTools/__init__.py
PyScriptTools/tools/SystemTools/__init__.py
PyScriptTools/utils/__init__.py
PyScriptTools/utils/dataclasses.py
PyScriptTools-4.3.13.dist-info/METADATA
PyScriptTools-4.3.13.dist-info/WHEEL
PyScriptTools-4.3.13.dist-info/top_level.txt
PyScriptTools-4.3.13.dist-info/RECORD
