Metadata-Version: 2.1
Name: PyScriptTools
Version: 4.3.13
Summary: Simple Python Package to Gather and Show Your System Info.
Author: Shervin Badanara (shervinbdndev)
Author-email: shervin2234@gmail.com
Maintainer: Shervin Badanara
License: MIT
Project-URL: Source, https://www.github.com/shervinbdndev/PyScriptTools/
Keywords: python,system,systeminfo,local ip,public ip,sockets,cpu info,gpu info,ram info,disk info
Platform: UNKNOWN
Classifier: Development Status :: 5 - Production/Stable
Classifier: Intended Audience :: Developers
Classifier: Programming Language :: Python :: 3
Classifier: Operating System :: Unix
Classifier: Operating System :: MacOS :: MacOS X
Classifier: Operating System :: Microsoft :: Windows
Requires-Dist: GPUtil
Requires-Dist: requests
Requires-Dist: sockets
Requires-Dist: colorama
Requires-Dist: python-cfonts
Requires-Dist: setuptools
Requires-Dist: wheel
Requires-Dist: getmac
Requires-Dist: psutil
Provides-Extra: dev
Requires-Dist: check-manifest ; extra == 'dev'
Provides-Extra: test
Requires-Dist: coverage ; extra == 'test'
